[{"Id":"one","Title":"Ivan","Content":"The best of the best!!\nVery vell!","AuthorId":"50fd3950-3598-4fb3-9d5d-be209df52319","Date":"16.03.2008"},{"Id":"one","Title":"Ivan","Content":"The best of the best!!\nVery vell!","AuthorId":"50fd3950-3598-4fb3-9d5d-be209df52319","Date":"16.03.2008"},{"Id":"123","Title":"4124","Content":"1241515qwefrsfsfsf","AuthorId":"242","Date":"fsdfsfsfsfsddcsc"},{"Id":"dgdf","Title":"gdfgd","Content":"dfgdfgdf","AuthorId":"dfgdfgdf","Date":"gdgdfdfg"},{"Id":"xcbxbdf","Title":"dfbdfbdfvb","Content":"dfvdfdbd","AuthorId":"dfbdfbdfbdf","Date":"dfbdfbdfbdf"},{"Id":"zxfasfas","Title":"cascacasca","Content":"acacascaca","AuthorId":"cacascacas","Date":"ascascascac"}]